<annotation>
	<folder>kakipi07</folder>
	<filename>IMG_20190521_194201(1).jpg</filename>
	<path>C:\Users\sasimo\Desktop\kakipi07\IMG_20190521_194201(1).jpg</path>
	<source>
		<database>Unknown</database>
	</source>
	<size>
		<width>1200</width>
		<height>1600</height>
		<depth>3</depth>
	</size>
	<segmented>0</segmented>
	<object>
		<name>peanut</name>
		<pose>Unspecified</pose>
		<truncated>0</truncated>
		<difficult>0</difficult>
		<bndbox>
			<xmin>856</xmin>
			<ymin>1206</ymin>
			<xmax>954</xmax>
			<ymax>1355</ymax>
		</bndbox>
	</object>
	<object>
		<name>peanut</name>
		<pose>Unspecified</pose>
		<truncated>0</truncated>
		<difficult>0</difficult>
		<bndbox>
			<xmin>552</xmin>
			<ymin>521</ymin>
			<xmax>658</xmax>
			<ymax>629</ymax>
		</bndbox>
	</object>
	<object>
		<name>peanut</name>
		<pose>Unspecified</pose>
		<truncated>0</truncated>
		<difficult>0</difficult>
		<bndbox>
			<xmin>801</xmin>
			<ymin>414</ymin>
			<xmax>918</xmax>
			<ymax>544</ymax>
		</bndbox>
	</object>
	<object>
		<name>peanut</name>
		<pose>Unspecified</pose>
		<truncated>0</truncated>
		<difficult>0</difficult>
		<bndbox>
			<xmin>1009</xmin>
			<ymin>523</ymin>
			<xmax>1122</xmax>
			<ymax>619</ymax>
		</bndbox>
	</object>
</annotation>
